mypy_gitlab_code_quality/__init__.py
mypy_gitlab_code_quality-1.3.0.dist-info/licenses/LICENSE
mypy_gitlab_code_quality-1.3.0.dist-info/METADATA
mypy_gitlab_code_quality-1.3.0.dist-info/WHEEL
mypy_gitlab_code_quality-1.3.0.dist-info/entry_points.txt
mypy_gitlab_code_quality-1.3.0.dist-info/top_level.txt
mypy_gitlab_code_quality-1.3.0.dist-info/RECORD
