Metadata-Version: 2.4
Name: mypy-gitlab-code-quality
Version: 1.3.0
Summary: Simple script to generate gitlab code quality report from output of mypy.
Author: OokamiTheLord
Author-email: Dmitry Samsonov <dmitriy.samsonov28@gmail.com>
License: MIT License
Project-URL: Homepage, https://github.com/soul-catcher/mypy-gitlab-code-quality
Project-URL: Bug Tracker, https://github.com/soul-catcher/mypy-gitlab-code-quality/issues
Keywords: gitlab,gitlab-ci,mypy,codequality
Classifier: Development Status :: 5 - Production/Stable
Classifier: License :: OSI Approved :: MIT License
Classifier: Operating System :: OS Independent
Classifier: Programming Language :: Python :: 3
Classifier: Programming Language :: Python :: 3.9
Classifier: Programming Language :: Python :: 3.10
Classifier: Programming Language :: Python :: 3.11
Classifier: Programming Language :: Python :: 3.12
Classifier: Programming Language :: Python :: 3.13
Requires-Python: >=3.9
License-File: LICENSE
Dynamic: license-file
